LICENSE
errorpages/__init__.py
errorpages/urls.py
giant_errorpages-0.1.0.dist-info/LICENSE
giant_errorpages-0.1.0.dist-info/WHEEL
giant_errorpages-0.1.0.dist-info/METADATA
giant_errorpages-0.1.0.dist-info/RECORD
