Metadata-Version: 2.1
Name: giant-errorpages
Version: 0.1.0
Summary: A small package to trigger specific non-200 HTTP responses in a Django application.
Home-page: https://github.com/giantmade/giant-errorpages
License: MIT
Keywords: error,404,403,500
Author: Jon Atkinson
Author-email: jon@giantmade.com
Requires-Python: >=3.6,<4.0
Classifier: Environment :: Console
Classifier: License :: OSI Approved :: MIT License
Classifier: Operating System :: OS Independent
Classifier: Programming Language :: Python :: 3
Classifier: Programming Language :: Python :: 3.6
Classifier: Programming Language :: Python :: 3.7
Classifier: Programming Language :: Python :: 3.8
Classifier: Topic :: Software Development :: Documentation
Classifier: Topic :: Software Development :: Libraries :: Python Modules
Project-URL: Repository, https://github.com/giantmade/giant-errorpages
